MANIFEST.in
README.rst
setup.cfg
setup.py
card_py_bot/__init__.py
card_py_bot/__main__.py
card_py_bot/bot.py
card_py_bot/config.py
card_py_bot/scrape.py
card_py_bot.egg-info/PKG-INFO
card_py_bot.egg-info/SOURCES.txt
card_py_bot.egg-info/dependency_links.txt
card_py_bot.egg-info/entry_points.txt
card_py_bot.egg-info/requires.txt
card_py_bot.egg-info/top_level.txt
card_py_bot/MANA_ICONS/1000000m.gif
card_py_bot/MANA_ICONS/10m.gif
card_py_bot/MANA_ICONS/11m.gif
card_py_bot/MANA_ICONS/12m.gif
card_py_bot/MANA_ICONS/13m.gif
card_py_bot/MANA_ICONS/14m.gif
card_py_bot/MANA_ICONS/15m.gif
card_py_bot/MANA_ICONS/16m.gif
card_py_bot/MANA_ICONS/1m.gif
card_py_bot/MANA_ICONS/2bm.gif
card_py_bot/MANA_ICONS/2gm.gif
card_py_bot/MANA_ICONS/2m.gif
card_py_bot/MANA_ICONS/2rm.gif
card_py_bot/MANA_ICONS/2um.gif
card_py_bot/MANA_ICONS/2wm.gif
card_py_bot/MANA_ICONS/3m.gif
card_py_bot/MANA_ICONS/4m.gif
card_py_bot/MANA_ICONS/5m.gif
card_py_bot/MANA_ICONS/6m.gif
card_py_bot/MANA_ICONS/7m.gif
card_py_bot/MANA_ICONS/8m.gif
card_py_bot/MANA_ICONS/9m.gif
card_py_bot/MANA_ICONS/Tap.gif
card_py_bot/MANA_ICONS/Untap.gif
card_py_bot/MANA_ICONS/bgm.gif
card_py_bot/MANA_ICONS/bm.gif
card_py_bot/MANA_ICONS/brm.gif
card_py_bot/MANA_ICONS/gm.gif
card_py_bot/MANA_ICONS/gum.gif
card_py_bot/MANA_ICONS/gwm.gif
card_py_bot/MANA_ICONS/rgm.gif
card_py_bot/MANA_ICONS/rm.gif
card_py_bot/MANA_ICONS/rwm.gif
card_py_bot/MANA_ICONS/ubm.gif
card_py_bot/MANA_ICONS/um.gif
card_py_bot/MANA_ICONS/urm.gif
card_py_bot/MANA_ICONS/wbm.gif
card_py_bot/MANA_ICONS/wm.gif
card_py_bot/MANA_ICONS/wum.gif