Metadata-Version: 1.1
Name: card-py-bot
Version: 3.1.4
Summary: A Discord Bot for embedding WOTC Magic card links into Discord
Home-page: https://github.com/nklapste/card-py-bot
Author: Nathan Klapstein
Author-email: nklapste@ualberta.ca
License: MIT
Download-URL: https://github.com/nklapste/card-py-bot/archive/3.1.4.tar.gz
Platform: UNKNOWN
Classifier: License :: OSI Approved :: MIT License
Classifier: Programming Language :: Python :: 3
Classifier: Programming Language :: Python :: 3.5
Classifier: Programming Language :: Python :: 3.6
